extrude_linestrips.py
extrude_linestrips-1.0.dist-info/WHEEL
extrude_linestrips-1.0.dist-info/METADATA
extrude_linestrips-1.0.dist-info/RECORD
